{
  "siteName": "Joana Sousa",
  "seoTitle": "Joana Sousa - Treino Terapêutico | Lisboa",
  "seoDescription": "Especialista em Treino Terapêutico com mais de 10 anos de experiência em transformar vidas através do fitness.",
  "seoKeywords": "treino terapêutico, personal training, fitness, Lisboa, treino personalizado, reabilitação, bem-estar",
  "footerBrandText": "Personal trainer dedicada a ajudar-te a alcançar os teus objetivos de fitness e bem-estar.",
  "copyrightText": "Joana Sousa",
  "copyrightNote": "Paulo Sousa"
}
